{
  "_id": "67861a904a380bbf080a364f",
  "title": "Vandana v",
  "key": "E",
  "isTranslation": false,
  "chords": true,
  "version": "version_3",
  "language": "ta",
  "lines": [
[
  {
    "label": "VERSE",
    "chords": [
      { "root": "E", "number": 1, "quality": "", "space": null },
      { "root": "A/E", "number": "4/1", "quality": "", "space": 20 }
    ],
    "lyrics": { 
      "en": "You Know Me Lord", 
      "hi": "" 
    },
    "translation": { "en": "", "hi": "" }
  },
  {
    "chords": [
      { "root": "B/E", "number": "5/1", "quality": "", "space": null },
            { "root": "E", "number": 1, "quality": "", "space": 23 }
    ],
    "lyrics": { 
      "en": "All Of My Life Is Yours", 
      "hi": "" 
    },
    "translation": { "en": "", "hi": "" }
  },
  {
    "chords": [{ "root": "A", "number": 4, "quality": "", "space": 10 }],
    "lyrics": { 
      "en": "I Lay My Love At Your Feet", 
      "hi": "" 
    },
    "translation": { "en": "", "hi": "" }
  },
  {
    "chords": [{ "root": "E/G#", "number": "1/3", "quality": "", "space": 10   }],
    "lyrics": { 
      "en": "My Friend And My King", 
      "hi": "" 
    },
    "translation": { "en": "", "hi": "" }
  },
  {
    "chords": [
      { "root": "F#", "number": "2", "quality": "m", "space": 10 },
      { "root": "B", "number": "5", "quality": "", "space": 25 }
    ],

    "lyrics": { 
      "en": "Your Voice, It Stills My Heart", 
      "hi": "" 
    },
    "translation": { "en": "", "hi": "" }
  },
  {
    "label": "PRE-CHORUS",
 "chords": [
      { "root": "A/C#", "number": "4/6", "quality": "", "space": 23 },
      { "root": "B/D#", "number": "5/7", "quality": "", "space": 10 },
      { "root": "E", "number": 1, "quality": "", "space": 15 }
    ],
    "lyrics": { 
      "en": "You’re The One, Who Holds My Hand", 
      "hi": "" 
    },
    "translation": { "en": "", "hi": "" }
  },
  {
    "chords": [
            { "root": "G#", "number": "3", "quality": "sus", "space": 23 },
      { "root": "G#/B#", "number": "3/5", "quality": "", "space": 10 },
      { "root": "C#", "number": 6, "quality": "m", "space": 10 }
    ],
    "lyrics": { 
      "en": "You’re The One, Who Walks Beside Me", 
      "hi": "" 
    },
    "translation": { "en": "", "hi": "" }
  },
  {
    "chords": [
            { "root": "F#", "number": 2, "quality": "m", "space": 23 },
      { "root": "B", "number": 5, "quality": "sus", "space": 10 },
      { "root": "B", "number": 5, "quality": "", "space": 10 }
    ],
    "lyrics": { 
      "en": "You Gave It All, To Draw Me Close", 
      "hi": "" 
    },
    "translation": { "en": "", "hi": "" },
    "break": "break"
  },



  {
    "label": "CHORUS",
    "chords": [
      { "root": "E", "number": 1, "quality": "", "space": 15 },
      { "root": "B/D#", "number": "5/7", "quality": "", "space": 35 }
    ],
    "lyrics": { 
      "en": "Here I Am, Standing In Your Sanctuary", 
      "hi": "" 
    },
    "translation": { "en": "", "hi": "" }
  },
  {
    "chords": [{ "root": "C#", "number": 6, "quality": "m", "space": 40 }],
    "lyrics": { 
      "en": "With Outstretched Hands,", 
      "hi": "" 
    },
    "translation": { "en": "", "hi": "" }
  },
  {
    "chords": [{ "root": "G#", "number": 3, "quality": "m", "space": 35 }],
    "lyrics": { 
      "en": "Drinking In Your Glory", 
      "hi": "" 
    },
    "translation": { "en": "", "hi": "" }
  },
  {
    "chords": [
      { "root": "A", "number": 4, "quality": "", "space": 25 },
      { "root": "B/A", "number": "5/4", "quality": "", "space": 20 }
  ],
    "lyrics": { 
      "en": "Where Your Love Overwhelms", 
      "hi": "" 
    },
    "translation": { "en": "", "hi": "" }
  },
  {
    "chords": [
      { "root": "G#", "number": 3, "quality": "m", "space": 15 },
      { "root": "C#", "number": 6, "quality": "m", "space": 15 }
    ],
    "lyrics": { 
      "en": "And Joy Overflows", 
      "hi": "" 
    },
    "translation": { "en": "", "hi": "" }
  },
  {
    "chords": [
      { "root": "F#", "number": 2, "quality": "m", "space": 15 },
      { "root": "B", "number": 5, "quality": "sus", "space": 20 },
      { "root": "B", "number": 5, "quality": "", "space": 15 }
    ],
    "lyrics": { 
      "en": "Here’s All Of Me, Take All Of Me", 
      "hi": "" 
    },
    "translation": { "en": "", "hi": "" },
    "break": "break"
  },






  {
        "chords": [
      { "root": "E", "number": 1, "quality": "", "space": 15 },
      { "root": "B/D#", "number": "5/7", "quality": "", "space": 35 }
    ],
    "lyrics": { 
      "en": "Here I Am, Dwelling In Our Secret Place", 
      "hi": "" 
    },
    "translation": { "en": "", "hi": "" }
  },
  {
    "chords": [
      { "root": "C#", "number": 6, "quality": "m", "space": 15 }
  ],
    "lyrics": { 
      "en": "All My Days,", 
      "hi": "" 
    },
    "translation": { "en": "", "hi": "" }
  },
  {
    "chords": [
      { "root": "G#", "number": 3, "quality": "m", "space": 30 },
      { "root": "E/G#", "number": "1/3", "quality": "", "space": 10 }
  ],
    "lyrics": { 
      "en": "I Long To See Your Face", 
      "hi": "" 
    },
    "translation": { "en": "", "hi": "" }
  },
  {
    "chords": [ { "root": "A", "number": 4, "quality": "", "space": 25 },
      { "root": "B/A", "number": "5/4", "quality": "", "space": 20 }],
    "lyrics": { 
      "en": "As The World Fades Away,", 
      "hi": "" 
    },
    "translation": { "en": "", "hi": "" }
  },
  {
    "chords": [{ "root": "G#", "number": 3, "quality": "m", "space": 15 },
      { "root": "C#", "number": 6, "quality": "m", "space": 15 }],
    "lyrics": { 
      "en": "Our Hearts In Embrace", 
      "hi": "" 
    },
    "translation": { "en": "", "hi": "" }
  },
  {
    "chords": [{ "root": "F#", "number": 2, "quality": "m", "space": 15 },
      { "root": "B", "number": 5, "quality": "sus", "space": 20 }],
    "lyrics": { 
      "en": "It’s You, All I Want Is You,", 
      "hi": "" 
    },
    "translation": { "en": "", "hi": "" }
  },
  {
    "chords": [{ "root": "E", "number": 1, "quality": "", "space": 30 }],
    "lyrics": { 
      "en": "Oh To Be With You", 
      "hi": "" 
    },
    "translation": { "en": "", "hi": "" }
  },
























































  {
    "label": "BRIDGE",
    "chords": [
      { "root": "A", "number": 4, "quality": "", "space": null },
      { "root": "B/A", "number": "3/4", "quality": "", "space": 35 }
    ],
    "lyrics": { 
      "en": "Lord I Give You My Heart", 
      "hi": "" 
    },
    "translation": { "en": "", "hi": "" }
  },
  {
    "chords": [
      { "root": "G#", "number": 3, "quality": "m", "space": 20 },
      { "root": "C#", "number": 6, "quality": "m", "space": 25 },
      { "root": "B", "number": 5, "quality": "", "space": 5 }
    ],
    "lyrics": { 
      "en": "Where Can I Go, From Your Presence", 
      "hi": "" 
    },
    "translation": { "en": "", "hi": "" }
  },
  {
    "chords": [{ "root": "A", "number": 4, "quality": "", "space": null },
      { "root": "B/A", "number": "3/4", "quality": "", "space": 40 }],
    "lyrics": { 
      "en": "Lord I Surrender My All", 
      "hi": "" 
    },
    "translation": { "en": "", "hi": "" }
  },
  {
    "chords": [{ "root": "G#", "number": 3, "quality": "m", "space": 10 },
      { "root": "C#", "number": 6, "quality": "m", "space": 25 },
      { "root": "B", "number": 5, "quality": "", "space": 5 }],
    "lyrics": {
      "en": "Just To Be Here, To Be With You", 
      "hi": "" 
    },
    "translation": { "en": "", "hi": "" }
  },
  {
    "chords": [
      { "root": "A", "number": 4, "quality": "", "space": 20 },
      { "root": "B", "number": 5, "quality": "", "space": 5 },
      { "root": "C#", "number": 6, "quality": "m", "space": 5 },
      { "root": "E/G#", "number": "1/3", "quality": "", "space": 5 }
  ],
    "lyrics": { 
      "en": "(To Be With You)", 
      "hi": "" 
    },
    "translation": { "en": "", "hi": "" }
  }
]



  ]
}
